MLXpress/__init__.py
MLXpress/bigdata.py
MLXpress/diabetes.py
MLXpress/getdata.py
MLXpress/gt.py
MLXpress/help.py
MLXpress/iris.py
MLXpress/math.py
MLXpress/ml.py
MLXpress/networkviz.py
MLXpress/preprocessing.py
MLXpress/stats.py
MLXpress/timeSeries.py
MLXpress/wine.py
MLXpressLatestVersion/__init__.py
MLXpressLatestVersion/diabetes.py
MLXpressLatestVersion/iris.py
MLXpressLatestVersion/math.py
MLXpressLatestVersion/pr.py
MLXpressLatestVersion/preprocessing.py
MLXpressLatestVersion/stats.py
MLXpressLatestVersion/test.py
MLXpressLatestVersion/wine.py
MLXpress-0.1.9.5.dist-info/METADATA
MLXpress-0.1.9.5.dist-info/WHEEL
MLXpress-0.1.9.5.dist-info/top_level.txt
MLXpress-0.1.9.5.dist-info/RECORD
