Metadata-Version: 2.1
Name: MLXpress
Version: 0.1.9.5
Summary: A powerful and user-friendly machine learning toolkit for data science and ML professionals to accelerate their workflow
Author: vinilg7
Author-email: vinilg7@gmail.com
Project-URL: Project Demo, https://colab.research.google.com/drive/1TItuBptf036xJwHypcn-SBiUM_kCfxZx?usp=sharing
Classifier: Development Status :: 3 - Alpha
Classifier: Intended Audience :: Developers
Classifier: License :: OSI Approved :: MIT License
Classifier: Programming Language :: Python :: 3
Classifier: Programming Language :: Python :: 3.8
Requires-Dist: scikit-learn
Requires-Dist: pandas
Requires-Dist: seaborn
Requires-Dist: matplotlib
Requires-Dist: numpy
Requires-Dist: scipy
Requires-Dist: yfinance
Requires-Dist: ccxt
Requires-Dist: forex-python
Requires-Dist: datetime
